jooyoungTest/test1.py
jooyoungTest/test2.py
newTest/test1.py
newTest/test2.py
jooyoungTest-0.0.0.2.dist-info/METADATA
jooyoungTest-0.0.0.2.dist-info/WHEEL
jooyoungTest-0.0.0.2.dist-info/top_level.txt
jooyoungTest-0.0.0.2.dist-info/RECORD
